django_sorcery/__init__.py
django_sorcery/__version__.py
django_sorcery/exceptions.py
django_sorcery/fields.py
django_sorcery/forms.py
django_sorcery/pytest_plugin.py
django_sorcery/routers.py
django_sorcery/shortcuts.py
django_sorcery/testing.py
django_sorcery/utils.py
django_sorcery/db/__init__.py
django_sorcery/db/composites.py
django_sorcery/db/fields.py
django_sorcery/db/middleware.py
django_sorcery/db/mixins.py
django_sorcery/db/models.py
django_sorcery/db/profiler.py
django_sorcery/db/query.py
django_sorcery/db/relations.py
django_sorcery/db/session.py
django_sorcery/db/signals.py
django_sorcery/db/sqlalchemy.py
django_sorcery/db/transaction.py
django_sorcery/db/url.py
django_sorcery/db/utils.py
django_sorcery/db/alembic/__init__.py
django_sorcery/db/alembic/base.py
django_sorcery/db/alembic/script.py.mako
django_sorcery/db/alembic/signals.py
django_sorcery/db/meta/__init__.py
django_sorcery/db/meta/base.py
django_sorcery/db/meta/column.py
django_sorcery/db/meta/composite.py
django_sorcery/db/meta/model.py
django_sorcery/db/meta/relations.py
django_sorcery/formsets/__init__.py
django_sorcery/formsets/base.py
django_sorcery/formsets/inline.py
django_sorcery/management/__init__.py
django_sorcery/management/alembic.py
django_sorcery/management/base.py
django_sorcery/management/commands/__init__.py
django_sorcery/management/commands/sorcery.py
django_sorcery/management/commands/sorcery_createall.py
django_sorcery/management/commands/sorcery_current.py
django_sorcery/management/commands/sorcery_downgrade.py
django_sorcery/management/commands/sorcery_dropall.py
django_sorcery/management/commands/sorcery_heads.py
django_sorcery/management/commands/sorcery_history.py
django_sorcery/management/commands/sorcery_revision.py
django_sorcery/management/commands/sorcery_stamp.py
django_sorcery/management/commands/sorcery_upgrade.py
django_sorcery/validators/__init__.py
django_sorcery/validators/base.py
django_sorcery/validators/runner.py
django_sorcery/views/__init__.py
django_sorcery-0.13.0.dist-info/AUTHORS.rst
django_sorcery-0.13.0.dist-info/LICENSE
django_sorcery-0.13.0.dist-info/METADATA
django_sorcery-0.13.0.dist-info/WHEEL
django_sorcery-0.13.0.dist-info/entry_points.txt
django_sorcery-0.13.0.dist-info/top_level.txt
django_sorcery-0.13.0.dist-info/RECORD
