Metadata-Version: 2.1
Name: django-sorcery
Version: 0.13.0
Summary: Django and SQLAlchemy integration
Home-page: https://github.com/shosca/django-sorcery
Author: Serkan Hosca
Author-email: serkan@hosca.com
License: MIT
Project-URL: Documentation, https://django-sorcery.readthedocs.io
Project-URL: Source, https://github.com/shosca/django-sorcery
Keywords: sqlalchemy django framework forms
Classifier: Development Status :: 4 - Beta
Classifier: Environment :: Web Environment
Classifier: Framework :: Django :: 1.11
Classifier: Framework :: Django :: 2.0
Classifier: Framework :: Django :: 2.1
Classifier: Framework :: Django :: 2.2
Classifier: Framework :: Django :: 3.0
Classifier: Framework :: Django :: 3.1
Classifier: Framework :: Django :: 3.2
Classifier: Framework :: Django :: 4.0
Classifier: Framework :: Django :: 4.1
Classifier: Framework :: Django :: 4.2
Classifier: Framework :: Django
Classifier: Intended Audience :: Developers
Classifier: License :: OSI Approved :: MIT License
Classifier: Natural Language :: English
Classifier: Operating System :: OS Independent
Classifier: Programming Language :: Python :: 3
Classifier: Programming Language :: Python :: 3 :: Only
Classifier: Programming Language :: Python :: 3.7
Classifier: Programming Language :: Python :: 3.8
Classifier: Programming Language :: Python :: 3.9
Classifier: Programming Language :: Python :: 3.10
Classifier: Programming Language :: Python :: 3.11
Classifier: Programming Language :: Python
Classifier: Topic :: Internet :: WWW/HTTP :: Dynamic Content
Classifier: Topic :: Internet :: WWW/HTTP :: WSGI
Classifier: Topic :: Software Development :: Libraries :: Application Frameworks
Classifier: Topic :: Software Development :: Libraries :: Python Modules
License-File: LICENSE
License-File: AUTHORS.rst
Requires-Dist: alembic
Requires-Dist: blinker
Requires-Dist: inflect
Requires-Dist: django
Requires-Dist: python-dateutil
Requires-Dist: sqlalchemy (<2)
